nati/__init__.py
nati/cisco_aci.py
nati/cisco_ise.py
nati/config_manager.py
nati/utils.py
nati-0.0.15.dist-info/METADATA
nati-0.0.15.dist-info/WHEEL
nati-0.0.15.dist-info/top_level.txt
nati-0.0.15.dist-info/RECORD
