Metadata-Version: 2.4
Name: nati
Version: 0.0.15
Summary: Network Analytics and Telemetry Interface (NATI) for gathering network information from various devices.
Author-email: Joshua James <josh@unobi.com>
License-Expression: MIT
Project-URL: Homepage, https://nati.unobi.com
Classifier: Development Status :: 1 - Planning
Classifier: Programming Language :: Python
Requires-Python: >=3.7
Requires-Dist: datetime
Requires-Dist: iptools
Requires-Dist: netmiko
Requires-Dist: requests
Requires-Dist: pymysql
